badgepy/__init__.py
badgepy/__main__.py
badgepy/badge-template-full.svg
badgepy/default-widths.json
badgepy/pil_text_measurer.py
badgepy/precalculate_text.py
badgepy/precalculated_text_measurer.py
badgepy/py.typed
badgepy/text_measurer.py
badgepy-1.2.0.dist-info/licenses/LICENSE
badgepy-1.2.0.dist-info/METADATA
badgepy-1.2.0.dist-info/WHEEL
badgepy-1.2.0.dist-info/entry_points.txt
badgepy-1.2.0.dist-info/top_level.txt
badgepy-1.2.0.dist-info/RECORD
