Metadata-Version: 2.4
Name: badgepy
Version: 1.2.0
Summary: A library and command-line tool for generating Github-style badges
Author-email: Brian Quinlan <brian@sweetapp.com>, Xianpeng Shen <xianpeng.shen@gmail.com>
License: 
Project-URL: source, https://github.com/shenxianpeng/badgepy
Project-URL: tracker, https://github.com/shenxianpeng/badgepy/issues
Keywords: github,gh-badges,badge,shield,status
Classifier: Development Status :: 5 - Production/Stable
Classifier: Intended Audience :: Developers
Classifier: License :: OSI Approved :: Apache Software License
Classifier: Programming Language :: Python :: 3.9
Classifier: Programming Language :: Python :: 3.10
Classifier: Programming Language :: Python :: 3.11
Classifier: Programming Language :: Python :: 3.12
Classifier: Programming Language :: Python :: 3.13
Classifier: Operating System :: OS Independent
Requires-Python: >=3.9
License-File: LICENSE
Requires-Dist: Jinja2<4,>=3
Requires-Dist: requests<3,>=2.22.0
Requires-Dist: filetype<2.0.0,>=1.2.0
Provides-Extra: pil-measurement
Requires-Dist: Pillow<12,>=6; extra == "pil-measurement"
Provides-Extra: dev
Requires-Dist: Flask>=2.0; extra == "dev"
Requires-Dist: fonttools>=3.26; extra == "dev"
Requires-Dist: nox; extra == "dev"
Requires-Dist: Pillow>=5; extra == "dev"
Requires-Dist: pytest>=3.6; extra == "dev"
Requires-Dist: xmldiff>=2.4; extra == "dev"
Dynamic: license-file
